bigdata/__init__.py
bigdata/spark/__init__.py
bridgtl_bgd_dp_python-0.0.2.dist-info/METADATA
bridgtl_bgd_dp_python-0.0.2.dist-info/WHEEL
bridgtl_bgd_dp_python-0.0.2.dist-info/top_level.txt
bridgtl_bgd_dp_python-0.0.2.dist-info/RECORD
