Metadata-Version: 2.1
Name: bridgtl-bgd-dp-python
Version: 0.0.2
Summary: Bank Raya Indonesia - Big Data Python Package
Author: Dafa Wiratama
Author-email: dafa.wiratama@bankraya.co.id
Maintainer: Dafa Wiratama
Maintainer-email: dafa.wiratama@bankraya.co.id
Provides-Extra: spark
Requires-Dist: pyspark ==3.5.1 ; extra == 'spark'
